media_control/__init__.py
media_control/app.py
media_control/static/index.css
media_control/static/keyboard.js
media_control/templates/index.html
media_control-0.0.2.dist-info/METADATA
media_control-0.0.2.dist-info/WHEEL
media_control-0.0.2.dist-info/entry_points.txt
media_control-0.0.2.dist-info/top_level.txt
media_control-0.0.2.dist-info/RECORD
